<?xml version="1.0" encoding="UTF-8"?>
<service xmlns="http://einfracentral.eu">
	<id>5.01</id>
	<url>http://www.prace-ri.eu/prace-project-access</url>
	<name>PRACE Project Access</name>
	<description>Project Access is the access to PRACE Tier-0 world class high performance computing (HPC) resources for projects, which use codes that have been previously tested and have demonstrated high scalability and optimisation. Preparatory Access is strongly recommended to collect technical data to support the request of resources. Proposals for Project Access must be based on computer codes and data ready to run on the Tier-0 systems. </description>
	<targetUsers>Scientists and researchers</targetUsers>
	<userValue>Access to Tier-0 resources</userValue>
	<providers><provider>prace</provider></providers>
	<lifeCycleStatus>Production</lifeCycleStatus>
	<trl>9</trl>
	<category>Compute</category>
	<relatedServices>Preparatory Access</relatedServices>
	<request>http://www.prace-ri.eu/application-guide</request>
	<userManual>http://www.prace-ri.eu/IMG/pdf/PRACE-Guide-for-Applicants-to-Tier-0-V2016.pdf</userManual>
	<termsOfUse>Acceptable use Policies of the hosting sites</termsOfUse>
	<funding>Hosting Members </funding>
</service>