<?xml version="1.0" encoding="UTF-8"?>
<service xmlns="http://einfracentral.eu">
    <id>05.09</id>
    <brandName>PATC</brandName>
    <tagline>-</tagline>
    <fullName>PRACE Advanced Training Centres</fullName>
    <description>Τhe PRACE Advanced Training Centres (PATCs) provide top-class education and training opportunities for
        computational scientists in Europe and are the primary source for PRACE training portal materials.
    </description>
    <targetUsers>Scientists and researchers</targetUsers>
    <provider>PRACE</provider>
    <fundingSources>EC and PRACE members</fundingSources>
    <webpage>https://events.prace-ri.eu/category/2/</webpage>
    <phase>Production</phase>
    <technologyReadinessLevel>9</technologyReadinessLevel>
    <category>Training</category>
    <relatedServices>Preparatory Access</relatedServices>
    <pricing>Free of charge</pricing>
    <termsOfUse>Acceptable use Policies of the hosting sites</termsOfUse>
</service>